module_process/__init__.py
module_process/main.py
module_process-0.1.0.dist-info/METADATA
module_process-0.1.0.dist-info/WHEEL
module_process-0.1.0.dist-info/RECORD
