Metadata-Version: 2.1
Name: module-process
Version: 0.1.0
Summary: 
Author: Lucas
Author-email: lucasarralt@gmail.com
Requires-Python: >=3.10,<4.0
Classifier: Programming Language :: Python :: 3
Classifier: Programming Language :: Python :: 3.10
Classifier: Programming Language :: Python :: 3.11
Classifier: Programming Language :: Python :: 3.12
Requires-Dist: azure-storage-blob (>=12.19.1,<13.0.0)
